{"vgg_16": {"img_8": {"label": 0, "label_name": "carpenter's kit"}, "img_10": {"label": 0, "label_name": "carpenter's kit"}, "img_5": {"label": 0, "label_name": "carpenter's kit"}, "img_7": {"label": 0, "label_name": "carpenter's kit"}, "img_4": {"label": 0, "label_name": "carpenter's kit"}, "img_3": {"label": 0, "label_name": "carpenter's kit"}, "img_2": {"label": 0, "label_name": "mosquito net"}, "img_6": {"label": 0, "label_name": "carpenter's kit"}, "img_1": {"label": 0, "label_name": "mosquito net"}, "img_9": {"label": 0, "label_name": "carpenter's kit"}}, "inception_resnet_v2": {"img_8": {"label": 0, "label_name": "triceratops"}, "img_10": {"label": 0, "label_name": "triceratops"}, "img_5": {"label": 0, "label_name": "digital watch"}, "img_7": {"label": 0, "label_name": "digital watch"}, "img_4": {"label": 0, "label_name": "chain saw"}, "img_3": {"label": 0, "label_name": "digital watch"}, "img_2": {"label": 0, "label_name": "chain saw"}, "img_6": {"label": 0, "label_name": "stretcher"}, "img_1": {"label": 0, "label_name": "swab"}, "img_9": {"label": 0, "label_name": "digital watch"}}, "resnet_v1_50": {"img_8": {"label": 0, "label_name": "loudspeaker"}, "img_10": {"label": 0, "label_name": "loudspeaker"}, "img_5": {"label": 0, "label_name": "rugby ball"}, "img_7": {"label": 0, "label_name": "rugby ball"}, "img_4": {"label": 0, "label_name": "loudspeaker"}, "img_3": {"label": 0, "label_name": "rugby ball"}, "img_2": {"label": 0, "label_name": "loudspeaker"}, "img_6": {"label": 0, "label_name": "loudspeaker"}, "img_1": {"label": 0, "label_name": "rugby ball"}, "img_9": {"label": 0, "label_name": "rugby ball"}}, "inception_v3": {"img_8": {"label": 0, "label_name": "sandbar"}, "img_10": {"label": 0, "label_name": "sandbar"}, "img_5": {"label": 0, "label_name": "sandbar"}, "img_7": {"label": 0, "label_name": "sandbar"}, "img_4": {"label": 0, "label_name": "sandbar"}, "img_3": {"label": 0, "label_name": "sandbar"}, "img_2": {"label": 0, "label_name": "sandbar"}, "img_6": {"label": 0, "label_name": "sandbar"}, "img_1": {"label": 0, "label_name": "sandbar"}, "img_9": {"label": 0, "label_name": "sandbar"}}, "resnet_v1_152": {"img_8": {"label": 0, "label_name": "reflex camera"}, "img_10": {"label": 0, "label_name": "reflex camera"}, "img_5": {"label": 0, "label_name": "ice lolly"}, "img_7": {"label": 0, "label_name": "ice lolly"}, "img_4": {"label": 0, "label_name": "reflex camera"}, "img_3": {"label": 0, "label_name": "ice lolly"}, "img_2": {"label": 0, "label_name": "reflex camera"}, "img_6": {"label": 0, "label_name": "reflex camera"}, "img_1": {"label": 0, "label_name": "ice lolly"}, "img_9": {"label": 0, "label_name": "ice lolly"}}}